main.py
fast_ap2_payment-0.1.0.dist-info/METADATA
fast_ap2_payment-0.1.0.dist-info/WHEEL
fast_ap2_payment-0.1.0.dist-info/top_level.txt
fast_ap2_payment-0.1.0.dist-info/RECORD
