Metadata-Version: 2.4
Name: fast-ap2-payment
Version: 0.1.0
Summary: Add your description here
Requires-Python: >=3.12
Requires-Dist: pebbling>=0.1.1
Requires-Dist: twine>=6.2.0
